shadecreed/__init__.py
shadecreed/__main__.py
shadecreed/__test__.py
shadecreed/app/__init__.py
shadecreed/app/app.py
shadecreed/cache/__init__.py
shadecreed/cache/cache.py
shadecreed/core/__init__.py
shadecreed/core/headers/__init__.py
shadecreed/core/headers/argue.py
shadecreed/core/headers/network/__init__.py
shadecreed/core/headers/network/proxy.py
shadecreed/core/middleware/__init__.py
shadecreed/core/middleware/drive.py
shadecreed/core/middleware/schedule.py
shadecreed/core/utils/__init__.py
shadecreed/core/utils/assemble.py
shadecreed/core/utils/base.py
shadecreed/core/utils/build.py
shadecreed/core/utils/parse.py
shadecreed/ux/__init__.py
shadecreed/ux/anime.py
shadecreed/ux/ascii.py
shadecreed/ux/process.py
shadecreed-1.14.10.dist-info/licenses/LICENSE
shadecreed-1.14.10.dist-info/METADATA
shadecreed-1.14.10.dist-info/WHEEL
shadecreed-1.14.10.dist-info/entry_points.txt
shadecreed-1.14.10.dist-info/top_level.txt
shadecreed-1.14.10.dist-info/RECORD
