Metadata-Version: 2.4
Name: shadecreed
Version: 1.14.10
Summary: A CLI framework for web application assessments and penetration testing — built with modularity, continuous maintenance, and frequent updates in mind.
Author: Shade
Author-email: adesolasherifdeen3@gmail.com
License: GPL-3.0
Project-URL: GitHub, https://github.com/harkerbyte
Project-URL: Facebook, https://facebook.com/harkerbyte
Project-URL: Whatsapp, https://whatsapp.com/channel/0029Vb5f98Z90x2p6S1rhT0S
Project-URL: Youtube, https://youtube.com/@harkerbyte
Project-URL: Instagram, https://instagram.com/harkerbyte
Classifier: License :: OSI Approved :: GNU General Public License v3 (GPLv3)
Classifier: Programming Language :: Python :: 3
Classifier: Programming Language :: Python :: 3.11
Classifier: Operating System :: OS Independent
Requires-Python: >=3.11
License-File: LICENSE
Requires-Dist: httpx
Requires-Dist: html5lib
Requires-Dist: jinja2
Requires-Dist: selenium==4.9.1
Requires-Dist: beautifulsoup4
Requires-Dist: shadeDB
Dynamic: author
Dynamic: author-email
Dynamic: classifier
Dynamic: description
Dynamic: description-content-type
Dynamic: license
Dynamic: license-file
Dynamic: project-url
Dynamic: requires-dist
Dynamic: requires-python
Dynamic: summary
